README.txt
bootstrap.py
buildout.cfg
setup.py
buildouts/base.cfg
buildouts/buildout-plone3.cfg
buildouts/buildout-plone4.cfg
collective/__init__.py
collective.updatelinksoncopy.egg-info/PKG-INFO
collective.updatelinksoncopy.egg-info/SOURCES.txt
collective.updatelinksoncopy.egg-info/dependency_links.txt
collective.updatelinksoncopy.egg-info/entry_points.txt
collective.updatelinksoncopy.egg-info/namespace_packages.txt
collective.updatelinksoncopy.egg-info/not-zip-safe
collective.updatelinksoncopy.egg-info/requires.txt
collective.updatelinksoncopy.egg-info/top_level.txt
collective/updatelinksoncopy/__init__.py
collective/updatelinksoncopy/configure.zcml
collective/updatelinksoncopy/edgecases.txt
collective/updatelinksoncopy/handlers.py
collective/updatelinksoncopy/referencefields.txt
collective/updatelinksoncopy/tests.py
collective/updatelinksoncopy/textlinks.txt
docs/HISTORY.txt
docs/INSTALL.txt
docs/LICENSE.GPL
docs/LICENSE.txt