Metadata-Version: 1.0
Name: collective.updatelinksoncopy
Version: 1.0b5
Summary: Update links to child objects in TextFields and ReferenceFields when an Archetypes based object is copied and pasted
Home-page: http://plone.org/products/collective.updatelinksoncopy
Author: Matt Halstead
Author-email: matt@elyt.com
License: GPL
Keywords: Plone Archetypes
Platform: UNKNOWN
Classifier: Framework :: Plone
Classifier: Programming Language :: Python
Classifier: Topic :: Software Development :: Libraries :: Python Modules
Classifier: License :: OSI Approved :: GNU General Public License (GPL)
